{
"wzw7m4or3jg5kdkbng7qdhlr":["307lloyd","307lloyd"],
"teaexcmdje4v62yamfebl6uq":["agentlloyd","Agent Lloyd "],
"ej7beohlmqxhvjezbqqcu4yn":["ajl","A.J Lloyd"],
"r4v5wkodkq6f7z62mg5j2c7y":["alexislloyd","Alexis Lloyd"],
"oklpnkwhf7yydidtff4ztpic":["alexlloyd","Alex Lloyd"],
"67c3jl7mnfnblujkudeqsdxp":["allorca","Antoine Llorca"],
"ixu5nhxsr6iffpadyuovpizn":["albertlloreta","Albert Lloreta"],
"7aybivblig5nn7twfphvujtb":["albaricocker","La Llorona"],
"og6cdbzbgejvmkoisuxogsfr":["albertlloret","Albert Lloret"],
"aktj7k272de5dcasyk264p4l":["amylloyd","Amy Lloyd"],
"ywdiykbb7fyqxuj36u4fpivk":["angipauly","Angi Pauly Llobet"],
"h2ghnkswxh6k3rzxxxvtsffe":["andrewlloydjones","Andrew Lloyd-Jones"],
"bebkghmxhmzpgwih6vm5al5f":["augustlod","Lloyd"],
"ltcoubkbdvv7wxfiv7fmc3mu":["babudanifrik","Dani Lloret"],
"pax2jdefgyusosbc5s2epl4i":["beachape.com","lloydmeta"],
"nqqpv5vybp4rnsydpcactc4i":["bethlloydlewis","Bethan Lloyd-Lewis"],
"hqmuknaoznuoqztxq4uiikho":["beckyl","Becky Lloyd"],
"qec4iwyp4tfgbo457rlt2fbv":["biglloyd","Getting Lloyd"],
"6ndbk456gevnaimv27352tnm":["bluem3llow","☢ BLOT-SKUNK !!! 🦨"],
"adwxfpanfof7iftsr6n6bbjc":["boyonabike62","John Lloyd"],
"kru4avgd6b4gxby5mjiirjsx":["bortxeta82","Borja Franco Llopus"],
"kdx7fft5osldb6zzupkuhbky":["brucewatkinson","Bruce Lloyd Watkinson"],
"yykxxybye2d65rmj2sqptjec":["brianmlloyd","Brian Lloyd"],
"qwu5f7632k2cfvptvk6vhc2u":["brianlloyd","Brian Lloyd"],
"nxrkntl5sxivuotdbklyslah":["brendanlloyd","Brendan Lloyd"],
"okkmpizp4dyodf5ll677rfep":"bsky-llogb-prdoq",
"ymokfkhwlehtkxoxmkjopczb":["c3llofrau","Anna"],
"g6x3gq7xu4e3gdixjai6xzsa":["cabaileylloyd","CA Bailey-Lloyd"],
"6px72ug2u64ks74vpzfvjkaa":["cactisun","Lloyd"],
"dd5tgg3iz4e7x7ngwfqwiegy":["ch1llout","CH1LL"],
"euloxmu6zzlzhi4gahypj3oy":["codenamezed","Zane Lloyd"],
"f6oc5ytwspmnr5hdek75pxi2":["cognisant2000","Ali Zartash Lloyd"],
"52bqkx735npjknx5tybsvyjz":["crossedbells","lloyd bannings"],
"tbowwoycq7r4psidx3y7sgml":["cymrubookman","David Lloyd "],
"2v3gcwc3fiqiv3ehnbdanevv":["dasme","Lloyd Hannesson"],
"3b53chq7s7a5gnp5syv4wvr6":["daneadventures","M Lloyd"],
"f6nxrfm5ebe6kxkjq4crz65d":["dianalloydbooks","Diana Lloyd"],
"a6rp64caec7mu6ibw2hhbjql":["dondepre","David Llort"],
"ge2ysdwgaki3jhd7ahteywyr":["dralexlloyd","Alex Lloyd"],
"g6jeq3ads24x5vo2un6mm4zq":["druidlloydnk","RevLloyd"],
"ew5jmfnscxnwdnyskwkv53i5":["dwlf","Lloyd Dewolf"],
"bpotgt73rzmq4e2jgsrwot5b":["eldenlord-lloyd","Lloyd"],
"sa4acbbxv2j3kiiydvxfwb73":["emmaplaysgreen","EmmaPlaysGreen(aka Lloer)"],
"6drxdaeatzuudxrucqlwjwgh":["fauxpar.se","wank lloyd fright"],
"4salp2t2cyrefrsonftfreio":["fernandollor","Fernando Llor "],
"whlopgzihyujsz7l4ckkwsga":["friskydeer","Lloyd's Bone Zone"],
"6ehaai7n6eu27fyscm23tn3p":["fraulloyd","FrauLloyd"],
"yyqnsibeppq35jiggiqb47sb":["ftlmechanic","Don Lloyd"],
"qsabkcoc5beblk2o6p2k7r4q":["garethlloydevans","Gareth Lloyd Evans"],
"4tscpinsmwvketig2lj6f3ru":["ginagoesoutside","Gina Lloyd"],
"glen5x3z6u4jhho4ewz6k7na":["girosintornillos","GiRo SiNToRNiLLoS™"],
"cpkc2uqmpd55mmd5mcjvw6pw":["glendasings","Glenda Lloyd"],
"kwxuzsyfo434yf56iqyjj5gn":["glloydking","George Lloyd-King"],
"5oqfo6wvsrwqzcaf2o7g6b2i":["goatllord","GoatLlord"],
"xsmsxu5eljzpdbgtgnxnwb6h":["graylien","Lloyd"],
"p75pgqqaidd6qipqpr6fcl7t":["guillermollorens","Guillermo Llorens"],
"umxa73hmvbajglmxsh6ajaya":["h0llowb0dies","v.l. parz"],
"x6pgbiddiytpt2m7wmw2ffqx":"h3llomrj",
"p7mnhhohk4gw5ccghuw3dw44":["h3llokittie","kittie"],
"zladlcyaimtttyo42gfglymr":["h3llobunny","bunny"],
"zoj7thmua2nlxxxx3w4fsst3":["h0llowreen","боку но пивоч"],
"iu5s4ggpkknzhx265tkniryp":["h3llokuni","  "],
"mj54lxoax4slzdrvz4mpjb6m":["helenell","Helen Lloyd"],
"lfxdnpy5g7hrgywpkadblul6":["houmanreporter","Lloyd Jacobson, MSW"],
"vrik2vplf34qwt44iynqgwfm":["iestyn.net","Iestyn Lloyd-Wilkins"],
"xa2hbgajh2bjo4dbglwbilrx":["imbrianlloyd","Brian Lloyd"],
"kv3yylsrvyva24veubvqfibm":["ionantolin","Ion Antolín Llorente "],
"zorkhjhafbu2jtapxht52gax":["irisllop","Iris Llop"],
"jl6ohvlyhb76mu55cyggkp72":["janeyllou","Janey Llou  "],
"kxf6qzhwj7dfgbtyhv22spns":["jamespblloyd","James Lloyd"],
"3oyjyqg55vldhn7p753w5ogd":["jasonthomasii","K3llo"],
"67xlvax5yko33gc5jitma2em":["jakelam2116","Jake Lloyd"],
"ywvydnqu74x6welajf2vjnci":["jacoblloyd","Jacob Lloyd"],
"layt3cfvkauwezaa2zqwtnm5":["jakelloydbacon","Jake Lloyd Bacon"],
"3q5fy3ey4jheojpalphbz2nb":["jamesldulin","James Lloyd Dulin "],
"6u466x4doyu3xizcp3ok4qtw":["jamesalloyd","James Lloyd "],
"jnvmgbqj4mznngant5t5i734":["jennmlloyd","Jenn Lloyd"],
"fwchek3beq5xz4oxobyzycwm":["jimlloyd","Jim Lloyd"],
"3os45so35c4thc2dviaohtfs":["jlloydsky","James Lloyd"],
"wsayl4cnn5vwabs6yr77jusg":["jllortocean","Joan Llort"],
"cdhrhzfm3sxwfjotuammhzzc":["joshualloyd","Joshua Lloyd"],
"hqh45mhccyl5dt2nh2wxbxrj":["jtlloyd3","James Lloyd"],
"7owkh4noqccjdkub5bbzqeg3":["kallos","Kállos"],
"m4eob2pq2u23bg65s7oefm7y":["karenlloyd","Karen Lloyd"],
"6remfpgctqxvgwa2byfmsnra":["kazh","Lloyd"],
"tt2krpcels6fzdwt5e2iold6":["kelas","Kelas Lloyd"],
"vud72qqk2xcdy33u6iyagemf":["kevinlovestech","Kevin Lloyd"],
"exsfiiofso2wd2uslbmosq4q":["kellylloyd","Kelly Lloyd"],
"k4ghbqndcsub6dalhdbqlfos":["kimj721","Kim Lloyd "],
"e62yknrh5irjst7qfspb3mxd":["klloyd","Kirsten Lloyd"],
"nxbmx2k3zst2ictzwqvpwnds":["kmlloyd","Kathryn Lloyd"],
"7tog3blqsjaj6nib4vqr4ws6":["kristinlloyd","Kristin Lloyd"],
"sf7cxznlbmqlrkbhvflt2u5m":["legollorchs","LegoLlorchs"],
"vjud3lqq3oveinylyvevbi67":["literaldad","Frank Lloyd Wrong"],
"xxwwgqpwt72zjtfqurdhzlhm":["lja","Lloyd"],
"e672p3cs3nrjz5qyxc4ughhh":["ljfrank","Lloyd Frank"],
"7ewdd6gmhv4dxuv4x3hg3t4c":["lloydshep","Lloyd Shepherd"],
"alkrrlehhitbrg3xvkvecjwj":["lloydcole","Lloyd Cole"],
"beiiaeloytmexw6pnt5u7eht":["llobrow","Call of Cthuluke"],
"cb64g5m7av6jzhrpx422uo6q":["lloyddabbler","lloyddabbler"],
"cxecl6t7jbq5njvpskmg6rj7":["lloydw","Lloyd Waldo "],
"fchp634yw6km3lhkrdbh6kmr":["llort","llorT"],
"iotsoz42yztf63bq5xcwlk4u":["lloid","Deltron Zero"],
"oznp4peezcyntainhkoxoocq":["lloyddobler89","Lloyd Dobler's Ghost"],
"phyctxq75m4ve3xx5okse2iu":["lloydhe","Lloyd"],
"rtkqj2stgsojekj7rf4vnmec":["lloyddeerboyo","Bleat-O Extraordinare "],
"ta264shv3iuwi7znf5fgx75d":["lloydknott","Lloyd Knott"],
"v4nxfh6p4r4mhialraghulh7":["lloydgeorge57","Lloyd Lewis 💙"],
"vcem2p4tjwjwzig6oyp322dq":["llori92","Llori dels Barret de Palla"],
"wfskgfqoyaleoioujx7bosxh":["lloyddavis","Lloyd Davis"],
"y5cvkr72qy2nlqgkbbr2qit7":["lloydeaves","Lloyd Eaves"],
"3gy57futh3brpdh575mdx2ft":["llpv","Llorenç"],
"xcuhej7hhw7c3kmwez2sxbnu":["llorca","Antoine Llorca"],
"774mo3vuwiyhcbp2oaa7iphq":["lloydtabb","lloyd tabb"],
"u4tscc6widtbn6ajjz5g5x6q":["lloyd","Lloyd"],
"cedbovqky3e4dwt2u3fxc4gu":["lloydk","LlK"],
"wadkbjzyuuhhqfa7vvv74fsa":["lloyddabbs","Lloyd Dabbs "],
"rbmd23lencscfvxfagruxs4d":["llopii","لپکشانی"],
"4fvtu47dqyhw3u2ar7fmqyrr":["llogiq","llogiq"],
"slwu6x4g6bokqfvpxtmw3asv":["llopatto","Lenny Lopatto"],
"ysafsqwagnijwwnxgvab6ph2":["llopab","pablo"],
"ekciewslkz7enivsmdmwp7zl":["llonewolfiee","Wolfie"],
"g62s5asurglfc347jt7hsqlf":["lloydjatkinson","Lloyd"],
"xwdnpqv4cg7c2bweycfvxkmq":["llogan","Logan"],
"e4yqv376dndpgfea7easgs3r":["lloydalter","Lloyd Alter"],
"dg2ys4ixvwbqcmqgcml64puo":"lloydi",
"5laajggkyfikwvv54f5dvtbt":"lloydcolezone",
"flhnxcfj7grokqfjixg5e3k6":"lloydsfault",
"ntqxruu2jzauidpxsq3pkosh":["lloydjnelson","Lloyd Nelson"],
"timpmx24yapmxnztylwlaw2s":"lloydashton",
"vm5urcf6vv6ewqsmm7y5e5bu":["lloydcoombes","Lloyd Coombes"],
"y27glumewds62syms2v7vwrq":["llovestarz","sunny"],
"uyrrxf4kbyawd6tacg6ggqk6":["lloydchang","Lloyd Chang"],
"ytfpllyyrraolhurczhummlu":"llooll",
"k7yxtfldqs7ipdgje72jra6e":["lloliveira","Leo"],
"ubjh3c63rixg7cp4nvr2cayl":["lloydberry","Lloyd Berry"],
"g7dc2cdaythn2muyq24abvjm":["llovepoketmon7","차지훈:모든것의신"],
"dqhfou2babfznqgkdmfruerd":["lloydsummers","Lloyd Summers"],
"q5lwsf4r67b7xx36fwuupcz3":"lloydatiku",
"l6s3yu3st4r43s6onpjwvuc3":"lloydx",
"sa4hl7tdqtlixsgh5fpg3lgl":["lloveruri","ary"],
"j7bh2wenjxhjqke4ulskrlez":"llonsby",
"kkpkldfvrcn3w5vvhkph7puc":"llopart",
"rt234l3jxqhr2y2vjyum2lql":"lloya",
"m42kmrz6bbr74mpwkuagdp7u":"lloydnotgeorge",
"oxrito2binsuvu2dp3wo33xk":["lloidffxi","Lloid"],
"v7urx5gpzd5cccrtbcr2tt2x":"llopatin",
"jludyllo6am7h4i53c3kldw4":["llorracanit","Tina"],
"zojxv5t24itn4633hb64socx":["lloydlately","Sawan"],
"4oq5hrbbuiyzy5ropejwsjp7":["lloyd13","Lloyd"],
"nffiufjnhjl7ofni5gy44whg":"lloydmoritz",
"cxvne35r2ptv4zfz4pfehiiz":"lloyds",
"3pszcqayohafg2qq2i4f2yjm":["lloydiejl","Lloydie"],
"d7q7tynnxmbiptpoipevwk7z":["lloydyp","Lloyd Pattison"],
"mg65jiv7cukxu6iopmc6vw6i":"llo",
"2pghyhoa4td7g426lapw33ia":["lloyd.blue","Lloyd"],
"6piyjxhwjxho7yisfjs6umf7":"lloyddotdev",
"ltevgtamnngvzegholej72o5":["lloydlocks","Lloyd Locks"],
"bup5k2jltlsafhjeiv6vgamr":["llorens","Sergi"],
"ndhu3a7bjm5bbtcfml3guyx4":"lloydvk",
"bdkbdsletqfruc2jlemyxs45":"llorentejavi",
"lxhlkjh65ddlgy6fr6nioisr":["lloyd6675","Lloyd6675"],
"ox437ml3zci3u6pbcx7oarfy":["lloverboy","todd 💤"],
"n7pdkzvmfscqpidlkltypzzd":["lloximporter.stickimporters.com","lloximporter"],
"bjznmgnrcr53utgvvmmy7afb":"llorar",
"hawxlkjn6voliiacvaapid4y":"lloidfanaccount",
"rbae3h6kepfujjzt4bejmc3b":["lloydchery","Lloyd Chéry "],
"kpb5oprreiey43j6tzc7navu":["lloydr","Lloyd_R"],
"sclckocj4xikf7qk2yldnsko":["lloraena","llorena"],
"ja6hnfxidkozauz7mdbjaceo":["lloydpancakes","Lloyd Pancakes"],
"itpbncocluq3hxprqmml4lk3":"lloai",
"e62qdhnj2vrzpuzs3s4o357r":"lloydtao",
"7jm433retveu4ug7mai56izw":"llourenco",
"2mp6fvpjuwodqrq32sogpmyt":"lloydsthumphrey",
"eewcabaokt5pcy4md2j3l2xo":["llowoll","すふれ"],
"kiiqbvlzmuhc7f4xamon6z2f":["llowry","LeeAnne Lowry"],
"dx5lzfnlwdvsxclld4wksntc":["lloquat","lloquat"],
"767yplnqgs32oxxxaardpv3x":["llodan","llodan"],
"z4gt6sb35vpvuc7ukqcmeoal":["lloyddboy","lloydDboy"],
"fj3horpan43hzswgpvtdorg5":["llovollsol","솔"],
"vleaefpanssqiqnrmwse6df5":"lloydfolfy7",
"6w7j6kwklijyjl3x3fxkudou":["llookkiijjuupp","푸구 PUGU"],
"qrqxmqwa3vbs5nvykt5eicqp":"llob",
"ugrouqq2n6kivop2r3dzahar":"lloydletta",
"nqhpx32rgrlfmqw4rn6jtzxi":"lloydzilla",
"of6xqu2ihj6mx2pukg2lanps":["lloydbowen","Lloyd Bowen"],
"dwhssgcgafg3vffynv6jrzcl":"lloyder",
"7gy4imtckptea53gqajjsnkh":["llorogarchando","LISA"],
"dx3jo76pq3kaazeg7vpmoc2k":["llorandoporel","josh"],
"3lsilyseqclhmkfzlfh2k3uw":"llojewski",
"nj6xys46iyjxwfraz2yqmo5k":["llopez","Lucia Lopez"],
"kp5u2ghzxacqssxejwam5mrv":["lloydglanville","Lloyd Glanville"],
"wnjvxz575cajwu4wujxnjk6s":"llordlloyd",
"o33aotocvuioyp7f6ldozvf5":"lloudmouth",
"xlza757s3di6klgflbumhajl":["lloyddy","Lloyddy"],
"xs5nbu76lhuxjbxad4mn2pri":["lloydenart","Llyoden"],
"ox5s26aitv2hd4blng5znok4":["lloydmac","LloydMac"],
"vpztbnqz3wycw4bnh4pi32lz":"llostagain",
"6iqr2nzriabe7porydf37mxr":["llonmalfarc","anthony"],
"pc62f4igrgsy7j6vdivvn3fz":["lloyddobler","Lloyd Dobler"],
"ejipwy6q7unry4v5oyf3s5kt":"llondo",
"hclagjeegaoj2ck3trjbtd2k":["llokationsfunktion","Allokationsfunktion"],
"6ghjjxcgh6xpzy2ajiz2mwys":["llojanes","Johannes Schmidt"],
"ytz7sp5i6psgbc5z7hwqb4gk":["llosef13","José Luis Forte"],
"2to62dmqgebjzsvlop2lu7pf":["lloydkeijzer","Lloyd"],
"bedz62fshhbx6yytcd57q2bx":["lloyd279","Lloyd"],
"7qilf5lqhuoezoswqqthwhod":"lloydinho",
"z2tmbcnmkqqfj5wsuralfmtn":"llolllollolloll",
"uqo364tzxbz3ydqvgq2zg7hn":"lloydbishop",
"tghf35lwon6pmh52aqgvpezm":"lloptr347",
"6qzqgdrwbuh5pyo6rh454fne":"lloydvo",
"253wnrnlvyf4z5wixm4qi6v4":["llovegood","Yvonne"],
"jsmz7yrvmc4scw2pxvuhwaj2":["llorithaine","geralt's defense attorney "],
"jj63u6iqbicawle3vzl7xdsw":["lloufast","Lindsey Fast"],
"57ucbb6jbxhk2b4ckrmx5xgr":["llororosa","María🗡️"],
"s4qdl7h3mw5ftbg6hjfkkwqu":"lloye",
"a7gagyjk3knc6vela53npxj6":["lloydb","Bryan L"],
"azetzvjidvnliit4avjw2f3h":"llouette",
"nujtomzh2aqmexddsnsu3vpf":["lloydlawliet","Lloydlawliet "],
"ngncyicsk2k5iqnlmsnua26i":["lloydbannings","LLOYD"],
"p5yab3vuqlq22ujetk5fms4w":"lloydd",
"ij3z5nctevxbov4nnmb65fdx":["lloydthebutler","Lloyd"],
"ofc5obrrqhc2eo3vhqi2xngc":["lloydnonsense","Lloyd's World of Nonsense"],
"chb4m7j2wnzjaqsu6oorcudm":["lloydzdavis","Lourd Davis"],
"h3f326z5nrq37vz6zl7w5eaz":["lloidy","Lloidy"],
"s5vsfhyqjwr5yt6p2i4ho6qx":"lloople",
"q7r36gnbpzqob5ljw2ltwz25":"lloydfolfy8",
"b7eiaxroaueyzzxb6izgppqp":["llow","llow"],
"lezvzlodcb7r2v6cviqdovzm":["lloromannic","★☆"],
"6ipxfjo5yiouaa4tpa7oikeu":["llok-lok","☆LLOK-LOK☆"],
"aorimx6u235nbcdinvyiw2pl":["lloyd-meliacea","Lloyd"],
"zxqkyheexbm5z6wbxirvv736":"llouis",
"m35iyyc6bvqam5lczavyaf7b":"lloafofbread",
"6mtgy6exmd4nvivivcs47rsk":["llouennearts","Ae"],
"lzbtsngaz73cdo4h3eigguu7":"llolly",
"2dintnbwtcqpy7fzuysy5w2z":"lloren",
"hacvajyuqkgnobrlfobrn7ar":["lloouuiiee","louie"],
"lv2ca5sgz4jws4wjtpk5vclv":["llopdelanit","Jorege"],
"if3vh5vsyb2ehwsthka4zqbc":"llopisd98",
"2czkha3yqzf6jfa7bvl77kj6":["lloydmaza","Lloyd"],
"s76uppqbzir6bayx4w6eajda":"lloydly",
"kp2znor5z42w6usj7igsbul6":["lloyfell","Lloyfell"],
"r5i6mktacnrx3l3e776vsqb6":["llorandingdong","maría"],
"3liahl2llwq4xidbv74ji6zd":"lloughlin",
"hza7okryzpwzd42ndhh546s4":"llordi",
"sznewl6mgifm3cemrduliz6l":"lloiss",
"2r6aaoxjlh6mwfagkjogcjqg":"lloydnicks",
"4g2c6psyyfpxasatmpzqzsta":"lloydj3d",
"d2tdlfrbvwb26jsg3apzztoq":"lloydcevans",
"puueqll4kibmjedxhw4gnwba":["louistrations.co.uk","Louis Lloyd-Judson"],
"iqc2cplce6tssm6sfmzhtiht":["lukelloyd","Luke Lloyd"],
"6lwgpwt2nugfoqc3ftrzcfio":["m3llowb1ue","ᴍᴇʟʟᴏᴡʙ!ᴜᴇ"],
"ksrqvc52xui3n7xyoxl4rrve":"marc-llovet",
"2ltp2bezlqbnquph2w7fnn75":["matthewlloydr","Matthew Lloyd Roberts"],
"dp6kqxsacv4kgtrttb2qedsa":["martinjlloyd","Martin J Lloyd"],
"bhl67dexfa2llnumwmvxobu2":["marshdam3llo","Marshy"],
"zahq4urpumfxhs3sahyzv3lf":["maylaen","Marsh.may.llow"],
"5g4bud26yfcuk5gfthrr464u":["meghanlloyd","Meghan Lloyd"],
"4umvu5h6k7usqhc6zltuzaqw":["mllompart","Miquel Llompart"],
"bfxy7mvce227eavfqed7xm75":["mllovet","Maria Llovet"],
"2o6ub2blbxfvkl6g6xlv3wi3":["mogster","Morgan Lloyd Malcolm"],
"sftlgsnm4ufkyim57r7ku5jr":["mountaincavalier","Carter Lloyd"],
"gr5onebc26iye2qyonygbnaw":["moeron42","Lloyd Gaultney "],
"vakamcce7dyk23r5uerttb5z":["mooselloyd","Moose Lloyd"],
"5x7o55k7g37sdlp2t3mwsrqr":["moyalloyd","Moya Lloyd"],
"7q36dcj6osnyis6247ddnkhf":["mrfivenines","Charlie Lloyd"],
"3zibcnfggecnfjoypwy36df4":["mxjlloyd","Jonathan Lloyd"],
"bgiw7f4zlzt53emq6cq56kry":["mybrainhurts","Lloyd Christmas"],
"dlibb6232uxrmdwlmkd6dk37":["nathanelloyd","Nathan Lloyd"],
"iwdmpq7s4zwhc4b3xbbe3pzs":["ngaihelloyd","Lloyd "],
"hq5j7rdzpmu4qhvsxwh4nzvq":["nicklloyd","Nick Lloyd"],
"buzrsjzwcxv43c3ktwzrbngw":["nicp","Nicolas Pröllochs"],
"uixfssojnbuiylbo7nyguzvi":["niknitro","Sr Lloret"],
"bli7i7kkjygawyqpuctkvmcm":["noahghola","Noah Lloyd"],
"u4ojeqlgxllop7pq3gtzwtwi":["novelcharacters","Hazel Meredith-Lloyd"],
"bfeo7ja6pv7zblrwjptr6xmb":["nullandlloyd","Lloyd Ennull"],
"h2d5adiyibfp7cxj3hieqzy4":["occamslaser","Evan Lloyd"],
"lyqccnvjrarb7qbwzvkpi426":["owenrichards","Owen Lloyd Richards"],
"k3ciqlqj6hg2fuzfndbp2h45":["palangano","Yago Llopis"],
"hdfen2rqp7h2zlstif6ihlgh":["patllombet","Pat Llombet"],
"j7q5u4mq4za2a3xuhxtr47yo":["pablolloret","Pablo Lloret"],
"ighqa4fhhbxllgnmyiwdvei5":["pancakez","Lloyd"],
"ro7qap4f2pwymtaxg5a5kiov":["pixalbunnii","PIXAL/Lloyd"],
"l46g5mmqetpn3obybjb3vkzk":["pinkflloyd95","Lloyd Kaplan"],
"yuzpbxroryceiu77oscjk24a":["pikachulloron","Mimikyu Lloron"],
"ni373u7m7ibpb353teq54rga":["propwash","Lloyd Christmas"],
"54yywylzcafgqamybtsrectm":["ratbear","Chris Lloyd"],
"n524dit5taaikocd7fwvun5k":["repeattofade","Owen Lloyd"],
"a42aay2lt7l3rj3u4hi4ajiv":["robinlloyd","Robin Lloyd"],
"m77zycr7xg4xrc6d7jyjzpdp":["roslynlloyd","Roslyn Lloyd"],
"b6ahico5vimjrujm74w2kcws":["rodthemaster","Rod Lloyd"],
"vms65xiicgdrrzgo7vllfjaw":["robertlloyd","Robert Lloyd"],
"b2aoshtozvi35qp7ibd6t3tg":["sallylld","Sally Lloyd"],
"bams4eymjogqariinhmsbneg":["scoooooot","Sam Lloyd"],
"3dqqjqv56wxhnl4ali543knt":["seraxia","John Lloyd"],
"5wvwrdc5ecixyxqsbsbsdqg4":["sharzydrawz","🐉Lloyd's Yang🐉"],
"krma42qmb5vczx7r4wbbgn7m":["shakeuphistory","Carol Ann Lloyd"],
"ivss5bgre24woysldgap4dsn":["silmogar","Silvia LLORANDO POR GOOD OMENS"],
"xtspj5gzg2d25um7gazp6mep":["slypumpkin","La Llorona"],
"44aq2l4h5tuzwhjs7n2467xj":["slkinsey","Samuel Lloyd Kinsey"],
"rjzublrztrc3iv7t6ge5ckyh":["stevecuff","Acid Lloyd Webber"],
"xwse6th6gzmx3inwfnlgvfig":["stug55","Stu Lloyd Gilkison"],
"ntgwapi7cnxq236a36bxwyrt":["susannahlloyd","Susannah Lloyd "],
"d7nw7jigynme2hxfnsr54hmm":["tatterededge","Lelainia Lloyd   🎙️♿️🥌🦄🇨🇦"],
"ya4gp6u6uxmkqge2p4nkpsxy":["techlloyd","Matt (Tech) Lloyd "],
"d57klo6dh2hxv3bydilgx6if":["terran.eastcrest.net","Terran Lloyd | Comms Open! ✉️🪶"],
"2mkio6xi5ej25yhhb5qqkniz":["thirdchildart","Meg Lloyd (she/her)"],
"pyrq4sozjskbnmjiz4wpupkz":["thethirstymage","David Lloyd"],
"6brmb7llgtvwq6p3nk7tlmap":["theolloydhughes","Theo Lloyd-Hughes"],
"e6pp3xmwzbo2fz6ezwxuvyvu":["thomaslloyd","Thomas Lloyd"],
"3jhrg6yr7uqj7cmhaw23a7jv":["themichaellloyd","Michael Lloyd LLC at your service"],
"y7gqfgg5wbcd22qxv2hbj4oq":["thelloydvoid","Lloyd"],
"23xjb5aeghfvfz7ewgcbbajz":["tomlloydwrites","Tom Lloyd"],
"scldlkfpobn6bgcanvdictqc":["totollygeek.com","ʞǝǝƃʎlloʇoʇ@"],
"usejsur2vlbqxjzxytxl47wg":["toil","Lloyd’s Soil"],
"fmfs6ciq5nkbrctcoer5jfhl":["tomlloyd","Tomos Lloyd"],
"mbcsdutv3hwtoheycx5r5lgh":["tonylloyd","Tony Lloyd"],
"vhtkalde47ozps2zuqsdwho5":["tormentx","llorón llorón kid"],
"brve2hiply3pizrh46gi7zsy":["tobylloyd","Toby Lloyd"],
"543mcwlvolpjph4xgppmwqoj":["ursinevulpine","Ursine Vulpine |  Frederick Lloyd"],
"7wyrnopiuqzoqdtb5wraoxlq":["vanity","lloyd howell “the mire mucko man”"],
"lblqy4swqfrk4qcfvedmkm7f":["verollorens","Verónica Lloréns-Rico"],
"limfugyea4ufzkg3ci4r63xe":["visuello","Vítor Visuêllo"],
"toyp4fmpiewmh6crvgvmxjqu":["villora","Víllora"],
"gd56fbnaopbt7ktvt3zdenjz":["victorllb","Victor Lloret Blackburn"],
"5dwc4cfcxvqrrbzmbatqayrw":["w1llow","Willow ☆"],
"lvulrkdvxzror7xrx3xivx3x":["wayfarer","Lloyd A. Meeker"],
"urvlq5nlkmywdzbinkkw52uo":["wi3llowbee","Wi3llowbee"],
"k6cc6hen4nwxzjchnqwfc2on":["willodavis","WiLLo Davis Ⓥ"],
"enm4evauhpjlzbg7dwuvpe5x":["wllofriu","Guille Llofriu Miret"],
"sqs2mis3e7n2i2mvahkqsi3m":["y3llowflash","Scott"],
"6acvuqjivbthxcsgp42ykay6":["y3llowflash274","Alex"],
"ot23ey6z3inba5iuiws3b3z7":["ylredroom","Yerson Lloyd 🔞"],
"7zfelziomih6ni2sjpck4fi5":["yves.lupine.gay","llop!"],
"ehpgfpv6n3ud3vkg2aufa57g":["zachlloydmt","Zach Lloyd"]
}
