{
"h3uzijzfpf66kastmrpbr4uu":["huldaholm","Hulda Hólmkelsdóttir"],
"awwien7bo7r7kq7wqehkcmrn":["jordilmk","Jordi LMK"],
"iacbqvfl73ogkrq6bgf5mwjc":["justlaurabee","Laurabee (LMK) Artist and designer! "],
"5vq7ipo443neiw2xutvdm5yr":["lmk","lmk"],
"ttvnxstupytujsvfiyw2l47c":["lmkey","Dr. Lora Key"],
"5nldkypgtxc25p7xkboql76s":["lmkhii","Let Me Know How It Is"],
"om3nuatjgkufj6gxl4ljqkos":"lmkulka",
"nyfityxdyxpjbhbo2un5crcx":["lmk111","Lawrence Kelty"],
"uzwkygtfllo4m252uwxjv2yq":"lmkcn",
"b3m6bcjehl5e7zfkxoemhtrx":["lmkuhn","Lena Kuhn"]
}
